simpleurdf/__init__.py
simpleurdf/__init__.pyi
simpleurdf/createpackage/__init__.py
simpleurdf/createpackage/create_pkg.py
simpleurdf/createpackage/ros2_command.sh
simpleurdf/interface/urdf_parser/urdf2_to_urdf.pyi
simpleurdf/interface/urdf_parser/urdf_parser.pyi
simpleurdf/pythonGenerator/FileGenerator.py
simpleurdf/pythonGenerator/__init__.py
simpleurdf/scripts/commands/create_pkg
simpleurdf/scripts/common
simpleurdf/scripts/create_pkg_.log
simpleurdf/scripts/create_pkg_robot_with_link_only.py.log
simpleurdf/scripts/python_templates/demo.launch.py
simpleurdf/scripts/python_templates/state_publisher.py
simpleurdf/scripts/robot_with_link_only.py
simpleurdf/scripts/robot_with_link_only_description/launch/demo.launch.py
simpleurdf/scripts/robot_with_link_only_description/package.xml
simpleurdf/scripts/robot_with_link_only_description/resource/robot_with_link_only_description
simpleurdf/scripts/robot_with_link_only_description/robot_with_link_only_description/__init__.py
simpleurdf/scripts/robot_with_link_only_description/robot_with_link_only_description/state_publisher.py
simpleurdf/scripts/robot_with_link_only_description/setup.cfg
simpleurdf/scripts/robot_with_link_only_description/setup.py
simpleurdf/scripts/robot_with_link_only_description/test/test_copyright.py
simpleurdf/scripts/robot_with_link_only_description/test/test_flake8.py
simpleurdf/scripts/robot_with_link_only_description/test/test_pep257.py
simpleurdf/scripts/simpleurdf
simpleurdf/scripts/simpleurdf-completion.bash
simpleurdf/urdf2model/.ropeproject/config.py
simpleurdf/urdf2model/.ropeproject/history
simpleurdf/urdf2model/.ropeproject/objectdb
simpleurdf/urdf2model/__init__.py
simpleurdf/urdf2model/basemodel.py
simpleurdf/urdf2model/metamodel.py
simpleurdf/urdf2model/model_factory.py
simpleurdf/urdf2model/predefinedcolors.py
simpleurdf/urdf_parser/.ropeproject/config.py
simpleurdf/urdf_parser/.ropeproject/history
simpleurdf/urdf_parser/.ropeproject/objectdb
simpleurdf/urdf_parser/__init__.py
simpleurdf-0.1.115.dist-info/WHEEL
simpleurdf-0.1.115.dist-info/METADATA
simpleurdf-0.1.115.dist-info/RECORD
